redditmedia/__init__.py
redditmedia/__main__.py
redditmedia/cli.py
redditmedia/py.typed
reddit_media-0.0.3.dist-info/LICENSE
reddit_media-0.0.3.dist-info/METADATA
reddit_media-0.0.3.dist-info/WHEEL
reddit_media-0.0.3.dist-info/top_level.txt
reddit_media-0.0.3.dist-info/RECORD
