Metadata-Version: 2.1
Name: reddit-media
Version: 0.0.3
Summary: Gets media URLs from Reddit Submission using Python Async PRAW
Home-page: https://github.com/capsey/reddit-media-py
Author: Caps Lock
Author-email: lockedcapsey@gmail.com
Classifier: Programming Language :: Python :: 3.7
Classifier: Programming Language :: Python :: 3.8
Classifier: Programming Language :: Python :: 3.9
Classifier: Programming Language :: Python :: 3.10
Classifier: License :: OSI Approved :: MIT License
Classifier: Operating System :: OS Independent
Requires-Python: >=3.7
License-File: LICENSE
Requires-Dist: asyncpraw (>=7.5.0)
Requires-Dist: aiohttp (>=3.8.3)
Requires-Dist: aiofiles (>=0.6.0)
Requires-Dist: click (>=8.1.3)
Requires-Dist: tqdm (>=4.64.1)
Provides-Extra: testing
Requires-Dist: flake8 (>=4.0.1) ; extra == 'testing'
Requires-Dist: tox (>=3.25.0) ; extra == 'testing'
Requires-Dist: pytest (>=7.1.2) ; extra == 'testing'
Requires-Dist: pytest-asyncio (>=0.19.0) ; extra == 'testing'
Requires-Dist: pytest-cov (>=3.0.0) ; extra == 'testing'
Requires-Dist: mypy (>=0.950) ; extra == 'testing'
Requires-Dist: types-aiofiles (>=22.1.0) ; extra == 'testing'
Requires-Dist: types-tqdm (>=4.64.6) ; extra == 'testing'
